kiwi_booster/__init__.py
kiwi_booster/common_utils/__init__.py
kiwi_booster/common_utils/geographic.py
kiwi_booster/common_utils/json.py
kiwi_booster/common_utils/loggers.py
kiwi_booster/common_utils/requests.py
kiwi_booster/common_utils/time.py
kiwi_booster/common_utils/video.py
kiwi_booster/decorators.py
kiwi_booster/gcp_utils/__init__.py
kiwi_booster/gcp_utils/bigquery.py
kiwi_booster/gcp_utils/kfp.py
kiwi_booster/gcp_utils/secrets.py
kiwi_booster/gcp_utils/storage.py
kiwi_booster/mcap_utils/__init__.py
kiwi_booster/mcap_utils/decode.py
kiwi_booster/ml_utils/__init__.py
kiwi_booster/ml_utils/benchmarks.py
kiwi_booster/ml_utils/prediction.py
kiwi_booster/slack_utils.py
kiwi_booster-0.4.0.post1.dist-info/LICENSE
kiwi_booster-0.4.0.post1.dist-info/METADATA
kiwi_booster-0.4.0.post1.dist-info/WHEEL
kiwi_booster-0.4.0.post1.dist-info/RECORD
