Metadata-Version: 2.1
Name: kiwi-booster
Version: 0.4.0.post1
Summary: Python utility functions and classes for KiwiBot AI&Robotics team
Author: Sebastian Hernandez
Author-email: juan.hernandez@kiwibot.con
Requires-Python: >=3.8,<3.13.0
Classifier: Programming Language :: Python :: 3
Classifier: Programming Language :: Python :: 3.8
Classifier: Programming Language :: Python :: 3.9
Classifier: Programming Language :: Python :: 3.10
Classifier: Programming Language :: Python :: 3.11
Classifier: Programming Language :: Python :: 3.12
Provides-Extra: video
Requires-Dist: google-auth (>=2.18.0,<3.0.0)
Requires-Dist: google-cloud-bigquery (>=3.10.0,<4.0.0)
Requires-Dist: google-cloud-secret-manager (>=2.16.1,<3.0.0)
Requires-Dist: google-cloud-storage (>=2.9.0,<3.0.0)
Requires-Dist: google-crc32c (>=1.5.0,<2.0.0)
Requires-Dist: ipregistry (>=3.2.0,<4.0.0)
Requires-Dist: kfp (==2.7.0)
Requires-Dist: mcap (>=1.1.1,<2.0.0)
Requires-Dist: mcap-ros2-support (>=0.5.3,<0.6.0)
Requires-Dist: moviepy (>=1.0.3,<2.0.0) ; extra == "video"
Requires-Dist: numpy (>=1.19,<2.0) ; python_version < "3.9"
Requires-Dist: numpy (>=1.23,<2.0) ; python_version >= "3.9"
Requires-Dist: opencv-python (>=4.9.0.80,<5.0.0.0) ; extra == "video"
Requires-Dist: pillow (>=10.2.0,<11.0.0)
Requires-Dist: python-path (>=0.1.3,<0.2.0)
Requires-Dist: slack-sdk (>=3.21.3,<4.0.0)
Requires-Dist: structlog (>=23.1.0,<24.0.0)
Requires-Dist: timezonefinder (==4.4.1)
Requires-Dist: tzlocal (>=5.2,<6.0)
